roa_checker/__init__.py
roa_checker/enums_and_dataclasses.py
roa_checker/py.typed
roa_checker/roa.py
roa_checker/roa_checker.py
roa_checker/roa_trie.py
roa_checker/roa_tries.py
roa_checker/roas_node.py
roa_checker/tests/__init__.py
roa_checker/tests/test_roa.py
roa_checker/tests/test_roa_checker.py
roa_checker-3.1.5.dist-info/licenses/LICENSE.txt
roa_checker-3.1.5.dist-info/METADATA
roa_checker-3.1.5.dist-info/WHEEL
roa_checker-3.1.5.dist-info/top_level.txt
roa_checker-3.1.5.dist-info/RECORD
